{
  "lastUpdated": "2026-01-31T01:06:51.462Z",
  "totalChannelsAnalyzed": 1,
  "totalVideos": 0,
  "totalShorts": 0,
  "totalRegularVideos": 0,
  "totalViewCount": 0,
  "totalLikeCount": 0,
  "averageViewsPerShort": 0,
  "topChannelsByShorts": [],
  "topShortsByViews": [],
  "recentShorts": [],
  "channelStats": [
    {
      "id": "UChlgI3UHCOnwUGzWzbJ3H5w",
      "title": " YTN",
      "description": "24시간 생중계되는 대한민국 대표 뉴스\nYTN 공식채널을 지금 바로 구독하세요\n\n▶ 구독하기 : http://goo.gl/Ytb5SZ\n\n▶ YTN 기사제보 안내\n- 홈페이지: https://mj.ytn.co.kr/mj/mj_write.php?sort=0\n- 모바일: YTN 앱의 제보하기\n- 이메일: social@ytn.co.kr\n- 전화: 02-398-8282 또는 8585 \n\n▶ 라이브 스트리밍 대체광고 및 콘텐츠 협업 문의\n - 이메일 : ljk@ytn.co.kr\n\n▶ 영상 사용 및 구매 문의\n - https://www.ytn.co.kr/business/sell_program.php\n",
      "customUrl": "@ytnnews24",
      "publishedAt": "2013-05-23T07:07:42Z",
      "subscriberCount": 5270000,
      "videoCount": 933576,
      "viewCount": 19286579727,
      "thumbnails": {
        "default": {
          "url": "https://yt3.ggpht.com/Sd77hfGXNh1K4VgLCnYVrzWVkUKh04N5VDClPweoP-sbaZXzH3llUz2W1N_-Z4RX5_XauYpvSQ=s88-c-k-c0x00ffffff-no-rj",
          "width": 88,
          "height": 88
        },
        "medium": {
          "url": "https://yt3.ggpht.com/Sd77hfGXNh1K4VgLCnYVrzWVkUKh04N5VDClPweoP-sbaZXzH3llUz2W1N_-Z4RX5_XauYpvSQ=s240-c-k-c0x00ffffff-no-rj",
          "width": 240,
          "height": 240
        },
        "high": {
          "url": "https://yt3.ggpht.com/Sd77hfGXNh1K4VgLCnYVrzWVkUKh04N5VDClPweoP-sbaZXzH3llUz2W1N_-Z4RX5_XauYpvSQ=s800-c-k-c0x00ffffff-no-rj",
          "width": 800,
          "height": 800
        }
      },
      "uploads": "UUhlgI3UHCOnwUGzWzbJ3H5w",
      "country": "KR",
      "videosAnalyzed": 0,
      "shortsCount": 0,
      "regularVideosCount": 0
    }
  ]
}