{
  "lastUpdated": "2026-07-11T01:44:56.178Z",
  "totalShorts": 8,
  "shorts": [
    {
      "id": "GJmyiqJHY5k",
      "channelId": "UCEsWtfVdAK8soPcDuVqu58g",
      "channelTitle": "엠뉴 | MBC경남 NEWS",
      "title": "한국형 차세대 고속 헬기 개발 시급",
      "description": "#블랙호크대체 #차세대고속헬기 #K방산 #한국항공우주 #헬리콥터 #미래무기 #국산화 #항공산업 #알기쉬운방산 #제2의보라매\n\n[ MBC경남 NEWS 구독하기 ]\n구독하기 : https://www.youtube.com/c/MBC경남News?sub_confirmation=1\n\n[ MBC경남 NEWS 제보하기 ]\n시청자 여러분들의 제보를 받습니다. 현장의 소리를",
      "publishedAt": "2026-07-10T06:30:50Z",
      "duration": "PT47S",
      "durationSeconds": 47,
      "viewCount": 5996,
      "likeCount": 75,
      "commentCount": 2,
      "thumbnails": {
        "default": {
          "url": "https://i.ytimg.com/vi/GJmyiqJHY5k/default.jpg",
          "width": 120,
          "height": 90
        },
        "medium": {
          "url": "https://i.ytimg.com/vi/GJmyiqJHY5k/mqdefault.jpg",
          "width": 320,
          "height": 180
        },
        "high": {
          "url": "https://i.ytimg.com/vi/GJmyiqJHY5k/hqdefault.jpg",
          "width": 480,
          "height": 360
        },
        "standard": {
          "url": "https://i.ytimg.com/vi/GJmyiqJHY5k/sddefault.jpg",
          "width": 640,
          "height": 480
        },
        "maxres": {
          "url": "https://i.ytimg.com/vi/GJmyiqJHY5k/maxresdefault.jpg",
          "width": 1280,
          "height": 720
        }
      },
      "tags": [
        "mbc경남",
        "엠비씨경남",
        "mbc경남 뉴스데스크",
        "뉴스데스크",
        "뉴스",
        "news 경남뉴스 경남",
        "엠뉴"
      ],
      "isShorts": true
    },
    {
      "id": "TfdyQcTP29g",
      "channelId": "UCEsWtfVdAK8soPcDuVqu58g",
      "channelTitle": "엠뉴 | MBC경남 NEWS",
      "title": "통영대전고속도로 화물차*공사 안전 차량 추돌.. 1명 부상(2026.7.10/뉴스데스크/MBC경남)",
      "description": "#통영대전고속도로 #산청휴게소 #교통사고 #화물차사고 #전방주시태만 #안전운전\n\n[ MBC경남 NEWS 구독하기 ]\n구독하기 : https://www.youtube.com/c/MBC경남News?sub_confirmation=1\n\n[ MBC경남 NEWS 제보하기 ]\n시청자 여러분들의 제보를 받습니다. 현장의 소리를 들으며\n항상 정확한 정보를 신속하게 보도하겠",
      "publishedAt": "2026-07-10T14:05:53Z",
      "duration": "PT28S",
      "durationSeconds": 28,
      "viewCount": 455,
      "likeCount": 6,
      "commentCount": 6,
      "thumbnails": {
        "default": {
          "url": "https://i.ytimg.com/vi/TfdyQcTP29g/default.jpg",
          "width": 120,
          "height": 90
        },
        "medium": {
          "url": "https://i.ytimg.com/vi/TfdyQcTP29g/mqdefault.jpg",
          "width": 320,
          "height": 180
        },
        "high": {
          "url": "https://i.ytimg.com/vi/TfdyQcTP29g/hqdefault.jpg",
          "width": 480,
          "height": 360
        },
        "standard": {
          "url": "https://i.ytimg.com/vi/TfdyQcTP29g/sddefault.jpg",
          "width": 640,
          "height": 480
        },
        "maxres": {
          "url": "https://i.ytimg.com/vi/TfdyQcTP29g/maxresdefault.jpg",
          "width": 1280,
          "height": 720
        }
      },
      "tags": [
        "mbc경남",
        "엠비씨경남",
        "mbc경남 뉴스데스크",
        "뉴스데스크",
        "뉴스",
        "news 경남뉴스 경남",
        "엠뉴"
      ],
      "isShorts": true
    },
    {
      "id": "PhFczpIN4jA",
      "channelId": "UCEsWtfVdAK8soPcDuVqu58g",
      "channelTitle": "엠뉴 | MBC경남 NEWS",
      "title": "하동군 공무원 153명 근무성적 임의변경..4명 징계 통보(2026.7.10/뉴스데스크/MBC경남)",
      "description": "#하동군 #하동군청 #근무성적평정 #인사비리 #경상남도감사위원회 #공직기강\n\n[ MBC경남 NEWS 구독하기 ]\n구독하기 : https://www.youtube.com/c/MBC경남News?sub_confirmation=1\n\n[ MBC경남 NEWS 제보하기 ]\n시청자 여러분들의 제보를 받습니다. 현장의 소리를 들으며\n항상 정확한 정보를 신속하게 보도하겠습니",
      "publishedAt": "2026-07-10T13:55:50Z",
      "duration": "PT40S",
      "durationSeconds": 40,
      "viewCount": 279,
      "likeCount": 4,
      "commentCount": 3,
      "thumbnails": {
        "default": {
          "url": "https://i.ytimg.com/vi/PhFczpIN4jA/default.jpg",
          "width": 120,
          "height": 90
        },
        "medium": {
          "url": "https://i.ytimg.com/vi/PhFczpIN4jA/mqdefault.jpg",
          "width": 320,
          "height": 180
        },
        "high": {
          "url": "https://i.ytimg.com/vi/PhFczpIN4jA/hqdefault.jpg",
          "width": 480,
          "height": 360
        },
        "standard": {
          "url": "https://i.ytimg.com/vi/PhFczpIN4jA/sddefault.jpg",
          "width": 640,
          "height": 480
        },
        "maxres": {
          "url": "https://i.ytimg.com/vi/PhFczpIN4jA/maxresdefault.jpg",
          "width": 1280,
          "height": 720
        }
      },
      "tags": [
        "mbc경남",
        "엠비씨경남",
        "mbc경남 뉴스데스크",
        "뉴스데스크",
        "뉴스",
        "news 경남뉴스 경남",
        "엠뉴"
      ],
      "isShorts": true
    },
    {
      "id": "kQdkHxrhhew",
      "channelId": "UCEsWtfVdAK8soPcDuVqu58g",
      "channelTitle": "엠뉴 | MBC경남 NEWS",
      "title": "홈플러스 피해업체에 경영안정자금*재기지원 등 특별지원(2026.7.10/뉴스데스크/MBC경남)",
      "description": "#홈플러스 #청산위기 #금융지원 #소상공인대출 #BNK경남은행 #경상남도\n\n[ MBC경남 NEWS 구독하기 ]\n구독하기 : https://www.youtube.com/c/MBC경남News?sub_confirmation=1\n\n[ MBC경남 NEWS 제보하기 ]\n시청자 여러분들의 제보를 받습니다. 현장의 소리를 들으며\n항상 정확한 정보를 신속하게 보도하겠습니다",
      "publishedAt": "2026-07-10T13:39:26Z",
      "duration": "PT32S",
      "durationSeconds": 32,
      "viewCount": 133,
      "likeCount": 2,
      "commentCount": 3,
      "thumbnails": {
        "default": {
          "url": "https://i.ytimg.com/vi/kQdkHxrhhew/default.jpg",
          "width": 120,
          "height": 90
        },
        "medium": {
          "url": "https://i.ytimg.com/vi/kQdkHxrhhew/mqdefault.jpg",
          "width": 320,
          "height": 180
        },
        "high": {
          "url": "https://i.ytimg.com/vi/kQdkHxrhhew/hqdefault.jpg",
          "width": 480,
          "height": 360
        },
        "standard": {
          "url": "https://i.ytimg.com/vi/kQdkHxrhhew/sddefault.jpg",
          "width": 640,
          "height": 480
        },
        "maxres": {
          "url": "https://i.ytimg.com/vi/kQdkHxrhhew/maxresdefault.jpg",
          "width": 1280,
          "height": 720
        }
      },
      "tags": [
        "mbc경남",
        "엠비씨경남",
        "mbc경남 뉴스데스크",
        "뉴스데스크",
        "뉴스",
        "news 경남뉴스 경남",
        "엠뉴"
      ],
      "isShorts": true
    },
    {
      "id": "aU6-DXhIw2k",
      "channelId": "UCEsWtfVdAK8soPcDuVqu58g",
      "channelTitle": "엠뉴 | MBC경남 NEWS",
      "title": "창원산단, 전국 첫 '피지컬AI 고속도로' 구축 본격화(2026.7.10/뉴스데스크/MBC경남)",
      "description": "#창원국가산단 #5G특화망 #피지컬AI #AX #제조업혁신 #경상남도\n\n[ MBC경남 NEWS 구독하기 ]\n구독하기 : https://www.youtube.com/c/MBC경남News?sub_confirmation=1\n\n[ MBC경남 NEWS 제보하기 ]\n시청자 여러분들의 제보를 받습니다. 현장의 소리를 들으며\n항상 정확한 정보를 신속하게 보도하겠습니다.\n",
      "publishedAt": "2026-07-10T13:33:52Z",
      "duration": "PT39S",
      "durationSeconds": 39,
      "viewCount": 96,
      "likeCount": 1,
      "commentCount": 1,
      "thumbnails": {
        "default": {
          "url": "https://i.ytimg.com/vi/aU6-DXhIw2k/default.jpg",
          "width": 120,
          "height": 90
        },
        "medium": {
          "url": "https://i.ytimg.com/vi/aU6-DXhIw2k/mqdefault.jpg",
          "width": 320,
          "height": 180
        },
        "high": {
          "url": "https://i.ytimg.com/vi/aU6-DXhIw2k/hqdefault.jpg",
          "width": 480,
          "height": 360
        },
        "standard": {
          "url": "https://i.ytimg.com/vi/aU6-DXhIw2k/sddefault.jpg",
          "width": 640,
          "height": 480
        },
        "maxres": {
          "url": "https://i.ytimg.com/vi/aU6-DXhIw2k/maxresdefault.jpg",
          "width": 1280,
          "height": 720
        }
      },
      "tags": [
        "mbc경남",
        "엠비씨경남",
        "mbc경남 뉴스데스크",
        "뉴스데스크",
        "뉴스",
        "news 경남뉴스 경남",
        "엠뉴"
      ],
      "isShorts": true
    },
    {
      "id": "C41qiRKfwi4",
      "channelId": "UCEsWtfVdAK8soPcDuVqu58g",
      "channelTitle": "엠뉴 | MBC경남 NEWS",
      "title": "희망 2026 이웃사랑 유공자 포상식(2026.7.10/뉴스데스크/MBC경남)",
      "description": "#희망2026 #이웃사랑유공자 #경남사회복지공동모금회 #사천시 #산청군 #경상남도\n\n[ MBC경남 NEWS 구독하기 ]\n구독하기 : https://www.youtube.com/c/MBC경남News?sub_confirmation=1\n\n[ MBC경남 NEWS 제보하기 ]\n시청자 여러분들의 제보를 받습니다. 현장의 소리를 들으며\n항상 정확한 정보를 신속하게 보도",
      "publishedAt": "2026-07-10T13:50:59Z",
      "duration": "PT29S",
      "durationSeconds": 29,
      "viewCount": 60,
      "likeCount": 1,
      "commentCount": 2,
      "thumbnails": {
        "default": {
          "url": "https://i.ytimg.com/vi/C41qiRKfwi4/default.jpg",
          "width": 120,
          "height": 90
        },
        "medium": {
          "url": "https://i.ytimg.com/vi/C41qiRKfwi4/mqdefault.jpg",
          "width": 320,
          "height": 180
        },
        "high": {
          "url": "https://i.ytimg.com/vi/C41qiRKfwi4/hqdefault.jpg",
          "width": 480,
          "height": 360
        },
        "standard": {
          "url": "https://i.ytimg.com/vi/C41qiRKfwi4/sddefault.jpg",
          "width": 640,
          "height": 480
        },
        "maxres": {
          "url": "https://i.ytimg.com/vi/C41qiRKfwi4/maxresdefault.jpg",
          "width": 1280,
          "height": 720
        }
      },
      "tags": [
        "mbc경남",
        "엠비씨경남",
        "mbc경남 뉴스데스크",
        "뉴스데스크",
        "뉴스",
        "news 경남뉴스 경남",
        "엠뉴"
      ],
      "isShorts": true
    },
    {
      "id": "RS7NSlYy2uw",
      "channelId": "UCEsWtfVdAK8soPcDuVqu58g",
      "channelTitle": "엠뉴 | MBC경남 NEWS",
      "title": "제1회 경상남도 관광의 날 기념식 개최(2026.7.10/뉴스데스크/MBC경남)",
      "description": "#경남관광의날 #경남관광주간 #경남여행 #창원컨벤션센터 #남해안관광 #경상남도\n\n[ MBC경남 NEWS 구독하기 ]\n구독하기 : https://www.youtube.com/c/MBC경남News?sub_confirmation=1\n\n[ MBC경남 NEWS 제보하기 ]\n시청자 여러분들의 제보를 받습니다. 현장의 소리를 들으며\n항상 정확한 정보를 신속하게 보도하겠",
      "publishedAt": "2026-07-10T13:47:23Z",
      "duration": "PT43S",
      "durationSeconds": 43,
      "viewCount": 59,
      "likeCount": 0,
      "commentCount": 2,
      "thumbnails": {
        "default": {
          "url": "https://i.ytimg.com/vi/RS7NSlYy2uw/default.jpg",
          "width": 120,
          "height": 90
        },
        "medium": {
          "url": "https://i.ytimg.com/vi/RS7NSlYy2uw/mqdefault.jpg",
          "width": 320,
          "height": 180
        },
        "high": {
          "url": "https://i.ytimg.com/vi/RS7NSlYy2uw/hqdefault.jpg",
          "width": 480,
          "height": 360
        },
        "standard": {
          "url": "https://i.ytimg.com/vi/RS7NSlYy2uw/sddefault.jpg",
          "width": 640,
          "height": 480
        },
        "maxres": {
          "url": "https://i.ytimg.com/vi/RS7NSlYy2uw/maxresdefault.jpg",
          "width": 1280,
          "height": 720
        }
      },
      "tags": [
        "mbc경남",
        "엠비씨경남",
        "mbc경남 뉴스데스크",
        "뉴스데스크",
        "뉴스",
        "news 경남뉴스 경남",
        "엠뉴"
      ],
      "isShorts": true
    },
    {
      "id": "y7s45wxkeaA",
      "channelId": "UChlgI3UHCOnwUGzWzbJ3H5w",
      "channelTitle": " YTN",
      "title": "트럼프, 휴전 종료 공식화 #shorts / YTN",
      "description": "최근 나토 정상회의 때 밝힌 '휴전 종료' 입장을 SNS를 통해 공식화한 것으로 보입니다.\n\n제작 : 송은혜\n\n\n\n▶ 기사 원문 : https://www.ytn.co.kr/_ln/0519_202607110833184639\n▶ 제보 하기 : https://mj.ytn.co.kr/mj/mj_write.php\n\n▣ YTN 유튜브 채널 구독 : http://goo",
      "publishedAt": "2026-07-11T01:41:54Z",
      "duration": "PT26S",
      "durationSeconds": 26,
      "viewCount": 0,
      "likeCount": 0,
      "commentCount": 0,
      "thumbnails": {
        "default": {
          "url": "https://i.ytimg.com/vi/y7s45wxkeaA/default.jpg",
          "width": 120,
          "height": 90
        },
        "medium": {
          "url": "https://i.ytimg.com/vi/y7s45wxkeaA/mqdefault.jpg",
          "width": 320,
          "height": 180
        },
        "high": {
          "url": "https://i.ytimg.com/vi/y7s45wxkeaA/hqdefault.jpg",
          "width": 480,
          "height": 360
        },
        "standard": {
          "url": "https://i.ytimg.com/vi/y7s45wxkeaA/sddefault.jpg",
          "width": 640,
          "height": 480
        },
        "maxres": {
          "url": "https://i.ytimg.com/vi/y7s45wxkeaA/maxresdefault.jpg",
          "width": 1280,
          "height": 720
        }
      },
      "tags": [
        "source:영상",
        "type:방송",
        "genre:기타",
        "format:기타",
        "트럼프",
        "이란",
        "휴전",
        "휴전종료",
        "공습",
        "휴전중공습",
        "미이란전쟁",
        "YTN"
      ],
      "isShorts": true
    }
  ]
}