{
  "lastUpdated": "2026-03-04T18:35:42.403Z",
  "totalShorts": 24,
  "shorts": [
    {
      "id": "RBrtWspbnSs",
      "channelId": "UCrxe-Msh2j6ICbfUaDJj81g",
      "channelTitle": "이슈카톡",
      "title": "서정욱도 '이대통령 잘해'~! '집을 팔다니'",
      "description": "서정욱과 보수들이 이재명 대통령 잘한다고 칭찬을~!!\n\n#분당 #아파트 #이재명 #이대통령 #대통령 #김혜경 #여사 #장동혁 #6채 #주택 #다주택자 #양도세중과 #주식 #etf #코스피 #코스닥 #부동산",
      "publishedAt": "2026-02-27T12:18:50Z",
      "duration": "PT28S",
      "durationSeconds": 28,
      "viewCount": 1650379,
      "likeCount": 39132,
      "commentCount": 1859,
      "thumbnails": {
        "default": {
          "url": "https://i.ytimg.com/vi/RBrtWspbnSs/default.jpg",
          "width": 120,
          "height": 90
        },
        "medium": {
          "url": "https://i.ytimg.com/vi/RBrtWspbnSs/mqdefault.jpg",
          "width": 320,
          "height": 180
        },
        "high": {
          "url": "https://i.ytimg.com/vi/RBrtWspbnSs/hqdefault.jpg",
          "width": 480,
          "height": 360
        },
        "standard": {
          "url": "https://i.ytimg.com/vi/RBrtWspbnSs/sddefault.jpg",
          "width": 640,
          "height": 480
        },
        "maxres": {
          "url": "https://i.ytimg.com/vi/RBrtWspbnSs/maxresdefault.jpg",
          "width": 1280,
          "height": 720
        }
      },
      "tags": [],
      "isShorts": true
    },
    {
      "id": "H059-HAmWCM",
      "channelId": "UCrxe-Msh2j6ICbfUaDJj81g",
      "channelTitle": "이슈카톡",
      "title": "국힘 행진, 깜박 집회신고 안해, 난장판 분위기, ㅋㅋㅋ",
      "description": "#국힘 #행진 #장동혁 #집회 #신고 #깜박 #사무처 #분위기 #난장판 #6채 #오피스텔 #이재명 #순방 #필리핀 #김혜경 #여사 #이대통령 #대통령 #이진관 #박성재 #국회 #추미애 #사법 #3법 #조희대 #부동산 #아파트 #주식 #주가 #코스피 #코스닥",
      "publishedAt": "2026-03-03T10:04:00Z",
      "duration": "PT28S",
      "durationSeconds": 28,
      "viewCount": 1334368,
      "likeCount": 33673,
      "commentCount": 2438,
      "thumbnails": {
        "default": {
          "url": "https://i.ytimg.com/vi/H059-HAmWCM/default.jpg",
          "width": 120,
          "height": 90
        },
        "medium": {
          "url": "https://i.ytimg.com/vi/H059-HAmWCM/mqdefault.jpg",
          "width": 320,
          "height": 180
        },
        "high": {
          "url": "https://i.ytimg.com/vi/H059-HAmWCM/hqdefault.jpg",
          "width": 480,
          "height": 360
        },
        "standard": {
          "url": "https://i.ytimg.com/vi/H059-HAmWCM/sddefault.jpg",
          "width": 640,
          "height": 480
        },
        "maxres": {
          "url": "https://i.ytimg.com/vi/H059-HAmWCM/maxresdefault.jpg",
          "width": 1280,
          "height": 720
        }
      },
      "tags": [],
      "isShorts": true
    },
    {
      "id": "vAlnK3bxds0",
      "channelId": "UCrxe-Msh2j6ICbfUaDJj81g",
      "channelTitle": "이슈카톡",
      "title": "시민 \"너나 잘해~!\" 고장난 송언석~! ㅋㅋㅋㅋㅋ",
      "description": "국힘 오늘 행진에서 한시민이 너나 잘해라고 하자, 회로가 고장난 송언석~!!\n\n#국힘 #송언석 #고장 #원내대표 #장동혁 #행진 #집회신고 #이재명 #이대통령 #대통령 #순방 #필리핀 #김혜경 #여사 #주식 #코스닥 #코스피 #부동산 #6채 #이진관 #판사 #검사 #법원 #재판 #조희대 #사법부",
      "publishedAt": "2026-03-03T12:28:39Z",
      "duration": "PT27S",
      "durationSeconds": 27,
      "viewCount": 1057422,
      "likeCount": 28431,
      "commentCount": 1496,
      "thumbnails": {
        "default": {
          "url": "https://i.ytimg.com/vi/vAlnK3bxds0/default.jpg",
          "width": 120,
          "height": 90
        },
        "medium": {
          "url": "https://i.ytimg.com/vi/vAlnK3bxds0/mqdefault.jpg",
          "width": 320,
          "height": 180
        },
        "high": {
          "url": "https://i.ytimg.com/vi/vAlnK3bxds0/hqdefault.jpg",
          "width": 480,
          "height": 360
        },
        "standard": {
          "url": "https://i.ytimg.com/vi/vAlnK3bxds0/sddefault.jpg",
          "width": 640,
          "height": 480
        },
        "maxres": {
          "url": "https://i.ytimg.com/vi/vAlnK3bxds0/maxresdefault.jpg",
          "width": 1280,
          "height": 720
        }
      },
      "tags": [],
      "isShorts": true
    },
    {
      "id": "bucaQmKfp28",
      "channelId": "UCrxe-Msh2j6ICbfUaDJj81g",
      "channelTitle": "이슈카톡",
      "title": "이대통령 집 팔아~! 무주택자~!! 이제 장동혁은??",
      "description": "이대통령이 분당의 아파트를 시세 보다 낮게 매물로 내놓았습니다. 신혼때부터 30년 가까이 살아온 집입니다, 국힘 장동혁도 이제 6채의 집을 팔아야 할 것입니다\n\n#이대통령 #분당집 #분당 #아파트 #매물 #팔아 #무주택 #이재명 #대통령 #주식 #부동산 #APT #다주택자 #투기 #삼성 #하이닉스 #etf #코스피 #코스닥",
      "publishedAt": "2026-02-27T09:06:42Z",
      "duration": "PT52S",
      "durationSeconds": 52,
      "viewCount": 925394,
      "likeCount": 44320,
      "commentCount": 3182,
      "thumbnails": {
        "default": {
          "url": "https://i.ytimg.com/vi/bucaQmKfp28/default.jpg",
          "width": 120,
          "height": 90
        },
        "medium": {
          "url": "https://i.ytimg.com/vi/bucaQmKfp28/mqdefault.jpg",
          "width": 320,
          "height": 180
        },
        "high": {
          "url": "https://i.ytimg.com/vi/bucaQmKfp28/hqdefault.jpg",
          "width": 480,
          "height": 360
        },
        "standard": {
          "url": "https://i.ytimg.com/vi/bucaQmKfp28/sddefault.jpg",
          "width": 640,
          "height": 480
        },
        "maxres": {
          "url": "https://i.ytimg.com/vi/bucaQmKfp28/maxresdefault.jpg",
          "width": 1280,
          "height": 720
        }
      },
      "tags": [],
      "isShorts": true
    },
    {
      "id": "tR2ZL-tM4oA",
      "channelId": "UCrxe-Msh2j6ICbfUaDJj81g",
      "channelTitle": "이슈카톡",
      "title": "필리핀 김혜경 여사 센스에 감탄~!!",
      "description": "핀리핀에 도착한 이재명 대통령 부부, 의장대 사열이 사작되자, 조용히 자리를 지켜주는데~\n\n#핀리핀 #이재명 #이대통령 #대통령 #방문 #김혜경 #여사 #의장대 #사열",
      "publishedAt": "2026-03-03T08:48:30Z",
      "duration": "PT59S",
      "durationSeconds": 59,
      "viewCount": 858972,
      "likeCount": 35484,
      "commentCount": 1112,
      "thumbnails": {
        "default": {
          "url": "https://i.ytimg.com/vi/tR2ZL-tM4oA/default.jpg",
          "width": 120,
          "height": 90
        },
        "medium": {
          "url": "https://i.ytimg.com/vi/tR2ZL-tM4oA/mqdefault.jpg",
          "width": 320,
          "height": 180
        },
        "high": {
          "url": "https://i.ytimg.com/vi/tR2ZL-tM4oA/hqdefault.jpg",
          "width": 480,
          "height": 360
        },
        "standard": {
          "url": "https://i.ytimg.com/vi/tR2ZL-tM4oA/sddefault.jpg",
          "width": 640,
          "height": 480
        },
        "maxres": {
          "url": "https://i.ytimg.com/vi/tR2ZL-tM4oA/maxresdefault.jpg",
          "width": 1280,
          "height": 720
        }
      },
      "tags": [],
      "isShorts": true
    },
    {
      "id": "dPokMwZdTfk",
      "channelId": "UCrxe-Msh2j6ICbfUaDJj81g",
      "channelTitle": "이슈카톡",
      "title": "이잼 부부 아파트 팔렸다~!!, 장동혁, 이준석 파묘",
      "description": "이재명 대통령, 김혜경 여사의 아파트가 오늘 팔렸다고 합니다. 내놓자 마자 팔렸네요 \n\n#이재명 #이대통령 #김혜경 #여사 #아파트 #매매 #코스피 #etf #주가 #주식 #장동혁 #6채 #분당 #부동산",
      "publishedAt": "2026-02-27T10:27:12Z",
      "duration": "PT41S",
      "durationSeconds": 41,
      "viewCount": 821540,
      "likeCount": 28912,
      "commentCount": 2630,
      "thumbnails": {
        "default": {
          "url": "https://i.ytimg.com/vi/dPokMwZdTfk/default.jpg",
          "width": 120,
          "height": 90
        },
        "medium": {
          "url": "https://i.ytimg.com/vi/dPokMwZdTfk/mqdefault.jpg",
          "width": 320,
          "height": 180
        },
        "high": {
          "url": "https://i.ytimg.com/vi/dPokMwZdTfk/hqdefault.jpg",
          "width": 480,
          "height": 360
        },
        "standard": {
          "url": "https://i.ytimg.com/vi/dPokMwZdTfk/sddefault.jpg",
          "width": 640,
          "height": 480
        },
        "maxres": {
          "url": "https://i.ytimg.com/vi/dPokMwZdTfk/maxresdefault.jpg",
          "width": 1280,
          "height": 720
        }
      },
      "tags": [],
      "isShorts": true
    },
    {
      "id": "Hd8Zz2I3nF4",
      "channelId": "UCrxe-Msh2j6ICbfUaDJj81g",
      "channelTitle": "이슈카톡",
      "title": "31절, 박수 안치는 송언석~! 대단한 국힘 대표~!!",
      "description": "3.1절 기념식에 이대통령과 독립유공자 후손들이 들어오는데, 박수 안치는 송언석\n\n#송언석 #국힘 #대표 #삼일절 #독립 #이재명 #이대통령 #대통령 #장동혁 #부동산 #6채 #아파트 #박수",
      "publishedAt": "2026-03-01T09:17:50Z",
      "duration": "PT58S",
      "durationSeconds": 58,
      "viewCount": 737892,
      "likeCount": 23050,
      "commentCount": 1712,
      "thumbnails": {
        "default": {
          "url": "https://i.ytimg.com/vi/Hd8Zz2I3nF4/default.jpg",
          "width": 120,
          "height": 90
        },
        "medium": {
          "url": "https://i.ytimg.com/vi/Hd8Zz2I3nF4/mqdefault.jpg",
          "width": 320,
          "height": 180
        },
        "high": {
          "url": "https://i.ytimg.com/vi/Hd8Zz2I3nF4/hqdefault.jpg",
          "width": 480,
          "height": 360
        },
        "standard": {
          "url": "https://i.ytimg.com/vi/Hd8Zz2I3nF4/sddefault.jpg",
          "width": 640,
          "height": 480
        },
        "maxres": {
          "url": "https://i.ytimg.com/vi/Hd8Zz2I3nF4/maxresdefault.jpg",
          "width": 1280,
          "height": 720
        }
      },
      "tags": [],
      "isShorts": true
    },
    {
      "id": "yhIM7B9-91M",
      "channelId": "UCrxe-Msh2j6ICbfUaDJj81g",
      "channelTitle": "이슈카톡",
      "title": "\"집팔자\"에 뇌정지 온 장동혁 ㅋㅋㅋ, 표정 웃겨~!!",
      "description": "한두자니의 \"집팔자\"라는 말에 뇌정지 온 장동혁 국힘 대표\n\n#한두자니 #집팔자 #뇌정지 #장동혁 #국힘 #대표 #송언석 #행진 #집회신고 #웃음 #표정 #개그 #이재명 #이대통령 #필리핀 #순방 #대통령 #김혜경 #여사 #주식 #코스피 #코스닥 #6채 #1채 #무주택 #윤석열 #김건희 #판사 #조희대",
      "publishedAt": "2026-03-03T13:28:13Z",
      "duration": "PT42S",
      "durationSeconds": 42,
      "viewCount": 710326,
      "likeCount": 30434,
      "commentCount": 1764,
      "thumbnails": {
        "default": {
          "url": "https://i.ytimg.com/vi/yhIM7B9-91M/default.jpg",
          "width": 120,
          "height": 90
        },
        "medium": {
          "url": "https://i.ytimg.com/vi/yhIM7B9-91M/mqdefault.jpg",
          "width": 320,
          "height": 180
        },
        "high": {
          "url": "https://i.ytimg.com/vi/yhIM7B9-91M/hqdefault.jpg",
          "width": 480,
          "height": 360
        },
        "standard": {
          "url": "https://i.ytimg.com/vi/yhIM7B9-91M/sddefault.jpg",
          "width": 640,
          "height": 480
        },
        "maxres": {
          "url": "https://i.ytimg.com/vi/yhIM7B9-91M/maxresdefault.jpg",
          "width": 1280,
          "height": 720
        }
      },
      "tags": [],
      "isShorts": true
    },
    {
      "id": "Hp5-qZWwl4s",
      "channelId": "UCrxe-Msh2j6ICbfUaDJj81g",
      "channelTitle": "이슈카톡",
      "title": "궁금한 장동혁, 확인하고 표정 썩어~ㅋㅋ",
      "description": "장동혁이 자신을 따라오는 피켓을 보고 표정이 썩는데\n\n#장동혁 #피켓 #집 #6채 #부동산 #오피스텔 #매매 #표정 #이재명 #이대통령 #대통령 #아파트 #투기 #주식 #코스피 #판사 #검사 #내란 #특검 #박성재 #윤석열 #김건희 #김성훈 #국힘",
      "publishedAt": "2026-03-04T08:05:54Z",
      "duration": "PT21S",
      "durationSeconds": 21,
      "viewCount": 665252,
      "likeCount": 11059,
      "commentCount": 227,
      "thumbnails": {
        "default": {
          "url": "https://i.ytimg.com/vi/Hp5-qZWwl4s/default.jpg",
          "width": 120,
          "height": 90
        },
        "medium": {
          "url": "https://i.ytimg.com/vi/Hp5-qZWwl4s/mqdefault.jpg",
          "width": 320,
          "height": 180
        },
        "high": {
          "url": "https://i.ytimg.com/vi/Hp5-qZWwl4s/hqdefault.jpg",
          "width": 480,
          "height": 360
        },
        "standard": {
          "url": "https://i.ytimg.com/vi/Hp5-qZWwl4s/sddefault.jpg",
          "width": 640,
          "height": 480
        },
        "maxres": {
          "url": "https://i.ytimg.com/vi/Hp5-qZWwl4s/maxresdefault.jpg",
          "width": 1280,
          "height": 720
        }
      },
      "tags": [],
      "isShorts": true
    },
    {
      "id": "QMjYZDocZUM",
      "channelId": "UCrxe-Msh2j6ICbfUaDJj81g",
      "channelTitle": "이슈카톡",
      "title": "1,400억 부자 안철수 '이대통령을 슈퍼리치로 공격'",
      "description": "1,400억을 가진 최고 부자 안철수가 이대통려을 슈퍼리치로 공격했습니다\n\n#안철수 #장동혁 #부동산 #6채 #오피스텔 #이재명 #이대통령 #대통령 #apt #주식 #코스피 #슈퍼리치 #분당",
      "publishedAt": "2026-03-02T05:13:22Z",
      "duration": "PT58S",
      "durationSeconds": 58,
      "viewCount": 625335,
      "likeCount": 23164,
      "commentCount": 2508,
      "thumbnails": {
        "default": {
          "url": "https://i.ytimg.com/vi/QMjYZDocZUM/default.jpg",
          "width": 120,
          "height": 90
        },
        "medium": {
          "url": "https://i.ytimg.com/vi/QMjYZDocZUM/mqdefault.jpg",
          "width": 320,
          "height": 180
        },
        "high": {
          "url": "https://i.ytimg.com/vi/QMjYZDocZUM/hqdefault.jpg",
          "width": 480,
          "height": 360
        },
        "standard": {
          "url": "https://i.ytimg.com/vi/QMjYZDocZUM/sddefault.jpg",
          "width": 640,
          "height": 480
        },
        "maxres": {
          "url": "https://i.ytimg.com/vi/QMjYZDocZUM/maxresdefault.jpg",
          "width": 1280,
          "height": 720
        }
      },
      "tags": [],
      "isShorts": true
    },
    {
      "id": "qrVZz8fHvcY",
      "channelId": "UCrxe-Msh2j6ICbfUaDJj81g",
      "channelTitle": "이슈카톡",
      "title": "안철수 따위가? 이잼의 28년 아파트 사연~!! [출처:매불쇼]",
      "description": "이재명 대통령의 28년 아파트 이야기, 어떻게 안철수, 장동혁이 비판?\n\n#이재명 #이대통령 #대통령 #28년 #성남 #분당 #안철수 #장동혁 #6채 #오피스텔",
      "publishedAt": "2026-03-02T07:49:06Z",
      "duration": "PT58S",
      "durationSeconds": 58,
      "viewCount": 475499,
      "likeCount": 18982,
      "commentCount": 1137,
      "thumbnails": {
        "default": {
          "url": "https://i.ytimg.com/vi/qrVZz8fHvcY/default.jpg",
          "width": 120,
          "height": 90
        },
        "medium": {
          "url": "https://i.ytimg.com/vi/qrVZz8fHvcY/mqdefault.jpg",
          "width": 320,
          "height": 180
        },
        "high": {
          "url": "https://i.ytimg.com/vi/qrVZz8fHvcY/hqdefault.jpg",
          "width": 480,
          "height": 360
        },
        "standard": {
          "url": "https://i.ytimg.com/vi/qrVZz8fHvcY/sddefault.jpg",
          "width": 640,
          "height": 480
        },
        "maxres": {
          "url": "https://i.ytimg.com/vi/qrVZz8fHvcY/maxresdefault.jpg",
          "width": 1280,
          "height": 720
        }
      },
      "tags": [],
      "isShorts": true
    },
    {
      "id": "xJ9NKboVpkU",
      "channelId": "UCrxe-Msh2j6ICbfUaDJj81g",
      "channelTitle": "이슈카톡",
      "title": "[퀴즈] 다음 중 거짓말쟁이는?  ① 송언석  ②주호영  ③ 나경원",
      "description": "국힘에서 대구경북 통합법 때문에 날리죠. 오늘 송언석 대표가 민주당 법사위가 반대한다고 했던데, 진짜 거짓말쟁이는 누굴까요?\n\n#송언석 #나경원 #주호영 #대구 #경북 #통합법 #법사위 #이재명 #이대통령 #대통령 #부동산 #장동혁 #6채",
      "publishedAt": "2026-03-01T11:19:20Z",
      "duration": "PT59S",
      "durationSeconds": 59,
      "viewCount": 412397,
      "likeCount": 7279,
      "commentCount": 691,
      "thumbnails": {
        "default": {
          "url": "https://i.ytimg.com/vi/xJ9NKboVpkU/default.jpg",
          "width": 120,
          "height": 90
        },
        "medium": {
          "url": "https://i.ytimg.com/vi/xJ9NKboVpkU/mqdefault.jpg",
          "width": 320,
          "height": 180
        },
        "high": {
          "url": "https://i.ytimg.com/vi/xJ9NKboVpkU/hqdefault.jpg",
          "width": 480,
          "height": 360
        },
        "standard": {
          "url": "https://i.ytimg.com/vi/xJ9NKboVpkU/sddefault.jpg",
          "width": 640,
          "height": 480
        },
        "maxres": {
          "url": "https://i.ytimg.com/vi/xJ9NKboVpkU/maxresdefault.jpg",
          "width": 1280,
          "height": 720
        }
      },
      "tags": [],
      "isShorts": true
    },
    {
      "id": "lyoMal-8OAE",
      "channelId": "UCrxe-Msh2j6ICbfUaDJj81g",
      "channelTitle": "이슈카톡",
      "title": "장동혁 오피스텔 안팔려서 어쩌나~!!",
      "description": "김민석 총리, 이대통령, 민주당 대표, 원내대표가 모두 합쳐서 2주택 ~!\n\n#이재명 #이대통령 #대통령 #김민석 #총리 #민주당 #원내대표 #대표 #정청래 #한병도 #장동혁 #6채 #오피스텔 #코스피 #코스닥 #이진관 #박성재 #판사",
      "publishedAt": "2026-03-02T12:57:07Z",
      "duration": "PT41S",
      "durationSeconds": 41,
      "viewCount": 361527,
      "likeCount": 12828,
      "commentCount": 630,
      "thumbnails": {
        "default": {
          "url": "https://i.ytimg.com/vi/lyoMal-8OAE/default.jpg",
          "width": 120,
          "height": 90
        },
        "medium": {
          "url": "https://i.ytimg.com/vi/lyoMal-8OAE/mqdefault.jpg",
          "width": 320,
          "height": 180
        },
        "high": {
          "url": "https://i.ytimg.com/vi/lyoMal-8OAE/hqdefault.jpg",
          "width": 480,
          "height": 360
        },
        "standard": {
          "url": "https://i.ytimg.com/vi/lyoMal-8OAE/sddefault.jpg",
          "width": 640,
          "height": 480
        },
        "maxres": {
          "url": "https://i.ytimg.com/vi/lyoMal-8OAE/maxresdefault.jpg",
          "width": 1280,
          "height": 720
        }
      },
      "tags": [],
      "isShorts": true
    },
    {
      "id": "KkhzsSLrETY",
      "channelId": "UCrxe-Msh2j6ICbfUaDJj81g",
      "channelTitle": "이슈카톡",
      "title": "도망가는 장동혁,~!! 화난 국힘의원들~!!",
      "description": "장동혁이 국힘의원들이 따지자, 도망을 가는데요\n\n#장동혁 #국힘 #의원들 #윤석열 #김건희 #도망 #6채 #부동산 #이재명 #이대통령 #대통령 #순방 #경제 #정치 #웃음 #아파트 #노모",
      "publishedAt": "2026-03-04T09:42:10Z",
      "duration": "PT41S",
      "durationSeconds": 41,
      "viewCount": 311792,
      "likeCount": 8851,
      "commentCount": 531,
      "thumbnails": {
        "default": {
          "url": "https://i.ytimg.com/vi/KkhzsSLrETY/default.jpg",
          "width": 120,
          "height": 90
        },
        "medium": {
          "url": "https://i.ytimg.com/vi/KkhzsSLrETY/mqdefault.jpg",
          "width": 320,
          "height": 180
        },
        "high": {
          "url": "https://i.ytimg.com/vi/KkhzsSLrETY/hqdefault.jpg",
          "width": 480,
          "height": 360
        },
        "standard": {
          "url": "https://i.ytimg.com/vi/KkhzsSLrETY/sddefault.jpg",
          "width": 640,
          "height": 480
        },
        "maxres": {
          "url": "https://i.ytimg.com/vi/KkhzsSLrETY/maxresdefault.jpg",
          "width": 1280,
          "height": 720
        }
      },
      "tags": [],
      "isShorts": true
    },
    {
      "id": "yZh11wdJcF4",
      "channelId": "UCrxe-Msh2j6ICbfUaDJj81g",
      "channelTitle": "이슈카톡",
      "title": "팔잘린 필리핀 노동자~ 변호한 이대통령 33년 만에 다시 만나~!",
      "description": "팔 잘리고 강제로 추방된 필리핀 노동자,  이대통령이 보상금을 받도록 변호 했는데요, 33년만에 다시 만났습니다\n\n#이대통령 #대통령 #이재명 #필리핀 #노동자 #산재 #보상금 #김혜경 #여사 #인연 #변호사 #6채 #부동산 #장동혁 #계엄 #내란 #윤석열 #김건희 #국힘 #행진 #바보 #웃음 #감동",
      "publishedAt": "2026-03-04T11:58:17Z",
      "duration": "PT57S",
      "durationSeconds": 57,
      "viewCount": 157748,
      "likeCount": 12903,
      "commentCount": 421,
      "thumbnails": {
        "default": {
          "url": "https://i.ytimg.com/vi/yZh11wdJcF4/default.jpg",
          "width": 120,
          "height": 90
        },
        "medium": {
          "url": "https://i.ytimg.com/vi/yZh11wdJcF4/mqdefault.jpg",
          "width": 320,
          "height": 180
        },
        "high": {
          "url": "https://i.ytimg.com/vi/yZh11wdJcF4/hqdefault.jpg",
          "width": 480,
          "height": 360
        },
        "standard": {
          "url": "https://i.ytimg.com/vi/yZh11wdJcF4/sddefault.jpg",
          "width": 640,
          "height": 480
        },
        "maxres": {
          "url": "https://i.ytimg.com/vi/yZh11wdJcF4/maxresdefault.jpg",
          "width": 1280,
          "height": 720
        }
      },
      "tags": [],
      "isShorts": true
    },
    {
      "id": "uS7ZpsxK_xU",
      "channelId": "UCrxe-Msh2j6ICbfUaDJj81g",
      "channelTitle": "이슈카톡",
      "title": "박상용 망했다, 김성태 '회유 녹취 나왔다'~!!",
      "description": "박상용 검사가 망한 것 같습니다. 김성태가 지인의 교도소 면회에서, 검사가 회유했다고 말했었고, 그게 언론사 녹취로 공개 되었습니다\n\n#박상용 #검사 #녹취 #김성태 #쌍방울 #대북송금 #검찰 #이재명 #이대통령 #대통령 #김혜경 #장동혁 #6채 #판사 #조희대 #윤석열 #김건희 #박성재 #한덕수 #내란 #계엄 #주식 #계엄",
      "publishedAt": "2026-03-04T10:19:21Z",
      "duration": "PT55S",
      "durationSeconds": 55,
      "viewCount": 149751,
      "likeCount": 12586,
      "commentCount": 554,
      "thumbnails": {
        "default": {
          "url": "https://i.ytimg.com/vi/uS7ZpsxK_xU/default.jpg",
          "width": 120,
          "height": 90
        },
        "medium": {
          "url": "https://i.ytimg.com/vi/uS7ZpsxK_xU/mqdefault.jpg",
          "width": 320,
          "height": 180
        },
        "high": {
          "url": "https://i.ytimg.com/vi/uS7ZpsxK_xU/hqdefault.jpg",
          "width": 480,
          "height": 360
        },
        "standard": {
          "url": "https://i.ytimg.com/vi/uS7ZpsxK_xU/sddefault.jpg",
          "width": 640,
          "height": 480
        },
        "maxres": {
          "url": "https://i.ytimg.com/vi/uS7ZpsxK_xU/maxresdefault.jpg",
          "width": 1280,
          "height": 720
        }
      },
      "tags": [],
      "isShorts": true
    },
    {
      "id": "vQGk4mPz88s",
      "channelId": "UCrxe-Msh2j6ICbfUaDJj81g",
      "channelTitle": "이슈카톡",
      "title": "민주당을 사랑한 스파이~! 장동혁~!?",
      "description": "게시판에 장동혁이 스파이가 아니냐는 글들이 올라오고 있습니다, 6채 빨지 말고, 끝까지 사수하세요\n장동혁에 국힘은 선거가 망했다는 데요\n\n#장동혁 #6채 #국힘 #부동산 #이재명 #이대통령 #대통령 #순방 #김혜경 #강남 #주식",
      "publishedAt": "2026-03-03T08:04:54Z",
      "duration": "PT58S",
      "durationSeconds": 58,
      "viewCount": 112500,
      "likeCount": 4727,
      "commentCount": 290,
      "thumbnails": {
        "default": {
          "url": "https://i.ytimg.com/vi/vQGk4mPz88s/default.jpg",
          "width": 120,
          "height": 90
        },
        "medium": {
          "url": "https://i.ytimg.com/vi/vQGk4mPz88s/mqdefault.jpg",
          "width": 320,
          "height": 180
        },
        "high": {
          "url": "https://i.ytimg.com/vi/vQGk4mPz88s/hqdefault.jpg",
          "width": 480,
          "height": 360
        },
        "standard": {
          "url": "https://i.ytimg.com/vi/vQGk4mPz88s/sddefault.jpg",
          "width": 640,
          "height": 480
        },
        "maxres": {
          "url": "https://i.ytimg.com/vi/vQGk4mPz88s/maxresdefault.jpg",
          "width": 1280,
          "height": 720
        }
      },
      "tags": [],
      "isShorts": true
    },
    {
      "id": "oDKN7gFB3Nk",
      "channelId": "UCrxe-Msh2j6ICbfUaDJj81g",
      "channelTitle": "이슈카톡",
      "title": "장동혁 ㅋㅋ, 웃겨 \"대통령 팔면 팔께요\"",
      "description": "이재명 대통령에게 장동혁이 했던 말을 가지고 이슈카톡이 만들었습니다\n\n#이대통령 #이재명 #대통령 #분당 #아파트 #매매 #장동혁 #6채 #노모 #부동산 #주식 #코스피 #코스닥 #주택 #행진 #한두자니 #지귀연 #판사 #검사 #윤석열 #김건희 #조희대 #국회 #국힘",
      "publishedAt": "2026-02-28T13:46:08Z",
      "duration": "PT22S",
      "durationSeconds": 22,
      "viewCount": 82778,
      "likeCount": 3491,
      "commentCount": 364,
      "thumbnails": {
        "default": {
          "url": "https://i.ytimg.com/vi/oDKN7gFB3Nk/default.jpg",
          "width": 120,
          "height": 90
        },
        "medium": {
          "url": "https://i.ytimg.com/vi/oDKN7gFB3Nk/mqdefault.jpg",
          "width": 320,
          "height": 180
        },
        "high": {
          "url": "https://i.ytimg.com/vi/oDKN7gFB3Nk/hqdefault.jpg",
          "width": 480,
          "height": 360
        },
        "standard": {
          "url": "https://i.ytimg.com/vi/oDKN7gFB3Nk/sddefault.jpg",
          "width": 640,
          "height": 480
        },
        "maxres": {
          "url": "https://i.ytimg.com/vi/oDKN7gFB3Nk/maxresdefault.jpg",
          "width": 1280,
          "height": 720
        }
      },
      "tags": [],
      "isShorts": true
    },
    {
      "id": "_shVUd70BDA",
      "channelId": "UCrxe-Msh2j6ICbfUaDJj81g",
      "channelTitle": "이슈카톡",
      "title": "장동혁의 목표, 꿈이 극우 교주? 국힘의 이만희가 목표?",
      "description": "장동혁의 꿈이 정권이 아니라, 극우 연합의 교주?가 목표인가?\n\n#장동혁 #신천지 #통일교 #교주 #꿈 #정권 #극우 #이준석 #나경원 #국힘 #행진 #6채 #주택 #집 #부동산 #이재명 #이대통령 #대통령 #윤석열 #김건희 #조희대 #법원 #국회 #추미애 #법사위 #사법 #이진관 #박성재",
      "publishedAt": "2026-03-04T07:23:29Z",
      "duration": "PT58S",
      "durationSeconds": 58,
      "viewCount": 80916,
      "likeCount": 2273,
      "commentCount": 169,
      "thumbnails": {
        "default": {
          "url": "https://i.ytimg.com/vi/_shVUd70BDA/default.jpg",
          "width": 120,
          "height": 90
        },
        "medium": {
          "url": "https://i.ytimg.com/vi/_shVUd70BDA/mqdefault.jpg",
          "width": 320,
          "height": 180
        },
        "high": {
          "url": "https://i.ytimg.com/vi/_shVUd70BDA/hqdefault.jpg",
          "width": 480,
          "height": 360
        },
        "standard": {
          "url": "https://i.ytimg.com/vi/_shVUd70BDA/sddefault.jpg",
          "width": 640,
          "height": 480
        },
        "maxres": {
          "url": "https://i.ytimg.com/vi/_shVUd70BDA/maxresdefault.jpg",
          "width": 1280,
          "height": 720
        }
      },
      "tags": [],
      "isShorts": true
    },
    {
      "id": "HIza3J96Uvg",
      "channelId": "UCrxe-Msh2j6ICbfUaDJj81g",
      "channelTitle": "이슈카톡",
      "title": "이대통령 멈춰세운, '아리랑', 필리핀이 준비한 이것~!",
      "description": "필리핀 대통령이 이대통령 내외를 위해 아리랑을 준비했습니다\n\n#필리핀 #대통령 #이재명 #이대통령 #대통령 #내외 #김혜경 #여사 #순방 #아리랑 #외교 #성과 #코스닥 #코스피 #부동산 #6채 #장동혁 #국힘 #판사 #검사 #특검 #대표 #국회 #이란 #트럼프",
      "publishedAt": "2026-03-04T02:29:45Z",
      "duration": "PT44S",
      "durationSeconds": 44,
      "viewCount": 49162,
      "likeCount": 2590,
      "commentCount": 136,
      "thumbnails": {
        "default": {
          "url": "https://i.ytimg.com/vi/HIza3J96Uvg/default.jpg",
          "width": 120,
          "height": 90
        },
        "medium": {
          "url": "https://i.ytimg.com/vi/HIza3J96Uvg/mqdefault.jpg",
          "width": 320,
          "height": 180
        },
        "high": {
          "url": "https://i.ytimg.com/vi/HIza3J96Uvg/hqdefault.jpg",
          "width": 480,
          "height": 360
        },
        "standard": {
          "url": "https://i.ytimg.com/vi/HIza3J96Uvg/sddefault.jpg",
          "width": 640,
          "height": 480
        },
        "maxres": {
          "url": "https://i.ytimg.com/vi/HIza3J96Uvg/maxresdefault.jpg",
          "width": 1280,
          "height": 720
        }
      },
      "tags": [],
      "isShorts": true
    },
    {
      "id": "ELcsbiB0S9s",
      "channelId": "UCrxe-Msh2j6ICbfUaDJj81g",
      "channelTitle": "이슈카톡",
      "title": "30억 이상, 1가구1주택도 양도세 중과해야~! 민주당은 입법 해야!",
      "description": "최근 몇년간 수십억씩 폭등한 강남 집값, 청년들의 결혼과 출산을 포기하게 만든 근원지, 30억이상 1가구 1주택도 양도세 중과하는 법안을 민주당은 당장 입법해야\n\n#양도세 #1가구1주택 #1주택 #양도세 #중과 #민주당 #입법 #이재명 #이대통령 #대통령 #주식 #부동산 #장동혁 #6채 #김상욱",
      "publishedAt": "2026-03-02T13:58:56Z",
      "duration": "PT52S",
      "durationSeconds": 52,
      "viewCount": 36298,
      "likeCount": 1636,
      "commentCount": 94,
      "thumbnails": {
        "default": {
          "url": "https://i.ytimg.com/vi/ELcsbiB0S9s/default.jpg",
          "width": 120,
          "height": 90
        },
        "medium": {
          "url": "https://i.ytimg.com/vi/ELcsbiB0S9s/mqdefault.jpg",
          "width": 320,
          "height": 180
        },
        "high": {
          "url": "https://i.ytimg.com/vi/ELcsbiB0S9s/hqdefault.jpg",
          "width": 480,
          "height": 360
        },
        "standard": {
          "url": "https://i.ytimg.com/vi/ELcsbiB0S9s/sddefault.jpg",
          "width": 640,
          "height": 480
        },
        "maxres": {
          "url": "https://i.ytimg.com/vi/ELcsbiB0S9s/maxresdefault.jpg",
          "width": 1280,
          "height": 720
        }
      },
      "tags": [],
      "isShorts": true
    },
    {
      "id": "pEjpdKSvcuA",
      "channelId": "UCgeOlLcX6PReHdWImEnUVTg",
      "channelTitle": "스픽스",
      "title": "필리핀에 울려 퍼진 아리랑 따라 부르는 김혜경 여사님",
      "description": "#shorts #김혜경 #이재명 #아리랑 #필리핀 #마르코스 #국빈 #외교\n\n🎉 스픽스 멤버십 [전용 회원 뱃지 + 이모티콘 출시] 리뉴얼 오픈🎉\nhttps://www.youtube.com/@SPEAKS_TV/join\n\n♣스픽스몰\nhttps://www.speaksmall.kr/\n\n♣️ 스픽스 유튜브 구독하기\nhttps://www.youtube.com/@",
      "publishedAt": "2026-03-04T06:07:52Z",
      "duration": "PT23S",
      "durationSeconds": 23,
      "viewCount": 28106,
      "likeCount": 653,
      "commentCount": 9,
      "thumbnails": {
        "default": {
          "url": "https://i.ytimg.com/vi/pEjpdKSvcuA/default.jpg",
          "width": 120,
          "height": 90
        },
        "medium": {
          "url": "https://i.ytimg.com/vi/pEjpdKSvcuA/mqdefault.jpg",
          "width": 320,
          "height": 180
        },
        "high": {
          "url": "https://i.ytimg.com/vi/pEjpdKSvcuA/hqdefault.jpg",
          "width": 480,
          "height": 360
        },
        "standard": {
          "url": "https://i.ytimg.com/vi/pEjpdKSvcuA/sddefault.jpg",
          "width": 640,
          "height": 480
        },
        "maxres": {
          "url": "https://i.ytimg.com/vi/pEjpdKSvcuA/maxresdefault.jpg",
          "width": 1280,
          "height": 720
        }
      },
      "tags": [
        "스픽스",
        "speaks",
        "더불어민주당",
        "민주당",
        "국민의힘",
        "여당",
        "야당",
        "여야",
        "정치대담",
        "정치",
        "경제대담",
        "경제",
        "윤석열",
        "윤대통령",
        "대통령",
        "정부",
        "보수",
        "진보",
        "중도",
        "전계완",
        "김건희",
        "건희사랑"
      ],
      "isShorts": true
    },
    {
      "id": "PiwKJjzoLe4",
      "channelId": "UCgeOlLcX6PReHdWImEnUVTg",
      "channelTitle": "스픽스",
      "title": "[소름주의] \"국민은 피눈물, 저들은 싱글벙글?\" 전쟁에 ”신났다“ 좋아죽는 사람들",
      "description": "#shorts #이재명 #경제 #주식 #배종찬 #부동산 #아파트 #전쟁 #이란 #미국 #트럼프 #코스피\n\n🎉 스픽스 멤버십 [전용 회원 뱃지 + 이모티콘 출시] 리뉴얼 오픈🎉\nhttps://www.youtube.com/@SPEAKS_TV/join\n\n♣스픽스몰\nhttps://www.speaksmall.kr/\n\n♣️ 스픽스 유튜브 구독하기\nhttps://w",
      "publishedAt": "2026-03-04T03:06:53Z",
      "duration": "PT47S",
      "durationSeconds": 47,
      "viewCount": 18873,
      "likeCount": 217,
      "commentCount": 16,
      "thumbnails": {
        "default": {
          "url": "https://i.ytimg.com/vi/PiwKJjzoLe4/default.jpg",
          "width": 120,
          "height": 90
        },
        "medium": {
          "url": "https://i.ytimg.com/vi/PiwKJjzoLe4/mqdefault.jpg",
          "width": 320,
          "height": 180
        },
        "high": {
          "url": "https://i.ytimg.com/vi/PiwKJjzoLe4/hqdefault.jpg",
          "width": 480,
          "height": 360
        },
        "standard": {
          "url": "https://i.ytimg.com/vi/PiwKJjzoLe4/sddefault.jpg",
          "width": 640,
          "height": 480
        },
        "maxres": {
          "url": "https://i.ytimg.com/vi/PiwKJjzoLe4/maxresdefault.jpg",
          "width": 1280,
          "height": 720
        }
      },
      "tags": [
        "스픽스",
        "speaks",
        "더불어민주당",
        "민주당",
        "국민의힘",
        "여당",
        "야당",
        "여야",
        "정치대담",
        "정치",
        "경제대담",
        "경제",
        "윤석열",
        "윤대통령",
        "대통령",
        "정부",
        "보수",
        "진보",
        "중도",
        "전계완",
        "김건희",
        "건희사랑"
      ],
      "isShorts": true
    },
    {
      "id": "J72PPAW2SHU",
      "channelId": "UCgeOlLcX6PReHdWImEnUVTg",
      "channelTitle": "스픽스",
      "title": "이재명 팬클럽 일부 작전세력? 김어준 “놀랍도록 유사..”",
      "description": "#shorts #이재명 #팬클럽 #친명 #반명 #정치 #김어준\n\n🎉 스픽스 멤버십 [전용 회원 뱃지 + 이모티콘 출시] 리뉴얼 오픈🎉\nhttps://www.youtube.com/@SPEAKS_TV/join\n\n♣스픽스몰\nhttps://www.speaksmall.kr/\n\n♣️ 스픽스 유튜브 구독하기\nhttps://www.youtube.com/@SPEAKS_",
      "publishedAt": "2026-03-04T03:58:14Z",
      "duration": "PT57S",
      "durationSeconds": 57,
      "viewCount": 13216,
      "likeCount": 297,
      "commentCount": 131,
      "thumbnails": {
        "default": {
          "url": "https://i.ytimg.com/vi/J72PPAW2SHU/default.jpg",
          "width": 120,
          "height": 90
        },
        "medium": {
          "url": "https://i.ytimg.com/vi/J72PPAW2SHU/mqdefault.jpg",
          "width": 320,
          "height": 180
        },
        "high": {
          "url": "https://i.ytimg.com/vi/J72PPAW2SHU/hqdefault.jpg",
          "width": 480,
          "height": 360
        },
        "standard": {
          "url": "https://i.ytimg.com/vi/J72PPAW2SHU/sddefault.jpg",
          "width": 640,
          "height": 480
        },
        "maxres": {
          "url": "https://i.ytimg.com/vi/J72PPAW2SHU/maxresdefault.jpg",
          "width": 1280,
          "height": 720
        }
      },
      "tags": [
        "스픽스",
        "speaks",
        "더불어민주당",
        "민주당",
        "국민의힘",
        "여당",
        "야당",
        "여야",
        "정치대담",
        "정치",
        "경제대담",
        "경제",
        "윤석열",
        "윤대통령",
        "대통령",
        "정부",
        "보수",
        "진보",
        "중도",
        "전계완",
        "김건희",
        "건희사랑"
      ],
      "isShorts": true
    }
  ]
}