{
  "lastUpdated": "2025-12-02T18:20:25.624Z",
  "totalShorts": 13,
  "shorts": [
    {
      "id": "JuCJHNVUNi0",
      "channelId": "UChlgI3UHCOnwUGzWzbJ3H5w",
      "channelTitle": " YTN",
      "title": "[속보][현장영상+] 추경호 \"원내대표로서 통상적 활동과 발언 꿰맞춰\" / YTN",
      "description": "[앵커]\n12·3 비상계엄 당시 계엄 해제 표결 참여를 방해한 혐의를 받는 국민의힘 추경호 의원이 구속 전 피의자 심문을 마쳤습니다.\n\n현장으로 가보겠습니다.\n\n[기자]\n의원님 혐의 어떻게 소명하셨습니까?\n\n[추경호 / 국민의힘 의원]\n성실하게 말씀을 드렸습니다.법인의 공정한 판단을 기대합니다.\n\n[기자]\n최후진술은 어떻게 하셨습니까? 고의로 표결 방해했다",
      "publishedAt": "2025-12-02T15:22:36Z",
      "duration": "PT38S",
      "durationSeconds": 38,
      "viewCount": 1275,
      "likeCount": 6,
      "commentCount": 4,
      "thumbnails": {
        "default": {
          "url": "https://i.ytimg.com/vi/JuCJHNVUNi0/default.jpg",
          "width": 120,
          "height": 90
        },
        "medium": {
          "url": "https://i.ytimg.com/vi/JuCJHNVUNi0/mqdefault.jpg",
          "width": 320,
          "height": 180
        },
        "high": {
          "url": "https://i.ytimg.com/vi/JuCJHNVUNi0/hqdefault.jpg",
          "width": 480,
          "height": 360
        },
        "standard": {
          "url": "https://i.ytimg.com/vi/JuCJHNVUNi0/sddefault.jpg",
          "width": 640,
          "height": 480
        },
        "maxres": {
          "url": "https://i.ytimg.com/vi/JuCJHNVUNi0/maxresdefault.jpg",
          "width": 1280,
          "height": 720
        }
      },
      "tags": [
        "source:영상",
        "type:방송",
        "genre:사회",
        "format:중계"
      ],
      "isShorts": true
    },
    {
      "id": "CYzf5IACZfo",
      "channelId": "UChlgI3UHCOnwUGzWzbJ3H5w",
      "channelTitle": " YTN",
      "title": "꼴찌 추락에 불화설 울산, 팬들에 사과 \"책임 통감\" / YTN",
      "description": "K리그 3연패를 이뤘던 디펜딩 챔피언에서 9위로 추락하며 2부 리그 강등을 겨우 피한 울산 구단이 팬들에게 사과했습니다.\n\n울산은 구단 SNS를 통해 실망스러운 성적으로 시즌을 마감해 팬들에게 죄송스러운 마음이라면서 뼈아픈 결과를 무겁게 받아들이고 책임을 통감하고 있다는 사과문을 올렸습니다.\n\n또, 시즌 중간에 감독을 두 차례 교체한 것은 전적으로 구단의 ",
      "publishedAt": "2025-12-02T14:37:42Z",
      "duration": "PT22S",
      "durationSeconds": 22,
      "viewCount": 588,
      "likeCount": 4,
      "commentCount": 3,
      "thumbnails": {
        "default": {
          "url": "https://i.ytimg.com/vi/CYzf5IACZfo/default.jpg",
          "width": 120,
          "height": 90
        },
        "medium": {
          "url": "https://i.ytimg.com/vi/CYzf5IACZfo/mqdefault.jpg",
          "width": 320,
          "height": 180
        },
        "high": {
          "url": "https://i.ytimg.com/vi/CYzf5IACZfo/hqdefault.jpg",
          "width": 480,
          "height": 360
        },
        "standard": {
          "url": "https://i.ytimg.com/vi/CYzf5IACZfo/sddefault.jpg",
          "width": 640,
          "height": 480
        },
        "maxres": {
          "url": "https://i.ytimg.com/vi/CYzf5IACZfo/maxresdefault.jpg",
          "width": 1280,
          "height": 720
        }
      },
      "tags": [
        "source:영상",
        "type:방송",
        "genre:스포츠",
        "format:기타",
        "person:이정미"
      ],
      "isShorts": true
    },
    {
      "id": "LM4v0SJQk0k",
      "channelId": "UChlgI3UHCOnwUGzWzbJ3H5w",
      "channelTitle": " YTN",
      "title": "\"윤석열, 담 넘는 국회의원 체포 지시\"...조지호 법정 증언 / YTN",
      "description": "[앵커]\n조지호 경찰청장이 계엄 당시 윤석열 전 대통령으로부터 담을 넘는 국회의원들을 체포하라는 지시를 받았다고 진술했습니다.\n\n이상민 전 장관 사건 재판에 증인으로 출석한 자리였는데요, 증언 모습 직접 보겠습니다.\n\n[조지호 / 경찰청장 (어제) : (윤석열 전 대통령이) 국회로 월담하는 의원들이 많다는 걸 아셨는지 '월담하고 이런 의원들을 다 잡아라, ",
      "publishedAt": "2025-12-02T15:36:55Z",
      "duration": "PT49S",
      "durationSeconds": 49,
      "viewCount": 455,
      "likeCount": 3,
      "commentCount": 1,
      "thumbnails": {
        "default": {
          "url": "https://i.ytimg.com/vi/LM4v0SJQk0k/default.jpg",
          "width": 120,
          "height": 90
        },
        "medium": {
          "url": "https://i.ytimg.com/vi/LM4v0SJQk0k/mqdefault.jpg",
          "width": 320,
          "height": 180
        },
        "high": {
          "url": "https://i.ytimg.com/vi/LM4v0SJQk0k/hqdefault.jpg",
          "width": 480,
          "height": 360
        },
        "standard": {
          "url": "https://i.ytimg.com/vi/LM4v0SJQk0k/sddefault.jpg",
          "width": 640,
          "height": 480
        },
        "maxres": {
          "url": "https://i.ytimg.com/vi/LM4v0SJQk0k/maxresdefault.jpg",
          "width": 1280,
          "height": 720
        }
      },
      "tags": [
        "source:영상",
        "type:방송",
        "genre:사회",
        "format:기타"
      ],
      "isShorts": true
    },
    {
      "id": "40ZIhG3EwFE",
      "channelId": "UChlgI3UHCOnwUGzWzbJ3H5w",
      "channelTitle": " YTN",
      "title": "폰세·안현민 조아제약 프로야구대상 대상 공동 수상...\"내년엔 MVP\" / YTN",
      "description": "한화 폰세와 kt 안현민이 조아제약 프로야구대상 시상식에서 공동 대상을 수상했습니다.\n\n안현민은 수상 소감에서 대상에 걸맞은 좋은 성적을 내겠다며, 내년에는 한국시리즈 MVP를 받고 싶다는 포부를 밝혔습니다.\n\n미국 출국으로 시상식에 불참한 폰세를 대신해 아내 엠마가 수상했고, 남편이 마운드에 오를 때마다 날개를 펼칠 수 있게 도와준 분들에게 영광을 돌린다",
      "publishedAt": "2025-12-02T14:33:45Z",
      "duration": "PT38S",
      "durationSeconds": 38,
      "viewCount": 420,
      "likeCount": 1,
      "commentCount": 1,
      "thumbnails": {
        "default": {
          "url": "https://i.ytimg.com/vi/40ZIhG3EwFE/default.jpg",
          "width": 120,
          "height": 90
        },
        "medium": {
          "url": "https://i.ytimg.com/vi/40ZIhG3EwFE/mqdefault.jpg",
          "width": 320,
          "height": 180
        },
        "high": {
          "url": "https://i.ytimg.com/vi/40ZIhG3EwFE/hqdefault.jpg",
          "width": 480,
          "height": 360
        },
        "standard": {
          "url": "https://i.ytimg.com/vi/40ZIhG3EwFE/sddefault.jpg",
          "width": 640,
          "height": 480
        },
        "maxres": {
          "url": "https://i.ytimg.com/vi/40ZIhG3EwFE/maxresdefault.jpg",
          "width": 1280,
          "height": 720
        }
      },
      "tags": [
        "source:영상",
        "type:방송",
        "genre:스포츠",
        "format:기타",
        "person:이정미"
      ],
      "isShorts": true
    },
    {
      "id": "3_KmoDnuyoQ",
      "channelId": "UChlgI3UHCOnwUGzWzbJ3H5w",
      "channelTitle": " YTN",
      "title": "민주, '조작 수사 진상규명' 국정조사 요구서 제출 / YTN",
      "description": "더불어민주당은 국민의힘이 대장동 사건과 관련한 국정조사 계획서를 국회에 내자 맞대응 성격의 별도 국조 요구서를 제출했습니다.\n\n민주당 원내대변인단은 오늘(2일) 정치 검찰의 조작 수사와 조작 기소의 진상규명에 방점을 찍은 국조 요구서를 국회 의안과에 냈습니다.\n\n관련해, 백승아 원내대변인은 기자들과 만나 국민의힘에선 대장동 항소 포기 프레임을 씌우면서 국조",
      "publishedAt": "2025-12-02T15:43:27Z",
      "duration": "PT36S",
      "durationSeconds": 36,
      "viewCount": 414,
      "likeCount": 2,
      "commentCount": 2,
      "thumbnails": {
        "default": {
          "url": "https://i.ytimg.com/vi/3_KmoDnuyoQ/default.jpg",
          "width": 120,
          "height": 90
        },
        "medium": {
          "url": "https://i.ytimg.com/vi/3_KmoDnuyoQ/mqdefault.jpg",
          "width": 320,
          "height": 180
        },
        "high": {
          "url": "https://i.ytimg.com/vi/3_KmoDnuyoQ/hqdefault.jpg",
          "width": 480,
          "height": 360
        },
        "standard": {
          "url": "https://i.ytimg.com/vi/3_KmoDnuyoQ/sddefault.jpg",
          "width": 640,
          "height": 480
        },
        "maxres": {
          "url": "https://i.ytimg.com/vi/3_KmoDnuyoQ/maxresdefault.jpg",
          "width": 1280,
          "height": 720
        }
      },
      "tags": [
        "source:영상",
        "type:방송",
        "genre:정치",
        "format:단신",
        "person:임성재"
      ],
      "isShorts": true
    },
    {
      "id": "xEXNrjERBUM",
      "channelId": "UChlgI3UHCOnwUGzWzbJ3H5w",
      "channelTitle": " YTN",
      "title": "[현장영상+] 이재명 정부 첫 예산안...728조 원 정부안 규모 유지 / YTN",
      "description": "[앵커]\n이재명 정부 첫 예산안이었는데요.\n\n728조 원 규모의 정부 예산안을 그대로 유지했고요.지역화폐와 국민성장펀드 등 이재명표 예산도 유지가 됐습니다.그리고 대통령실 특활비 82억 원이 복구됐고.\n\n다만 AI 예산 일부는 감액됐다는 점까지 전해드립니다.그럼 조금 전 본회의가 통과됐던 현장으로 가보겠습니다.\n\n[우원식 / 국회의장]\n그러면 국회법 제 9",
      "publishedAt": "2025-12-02T15:01:37Z",
      "duration": "PT56S",
      "durationSeconds": 56,
      "viewCount": 344,
      "likeCount": 2,
      "commentCount": 4,
      "thumbnails": {
        "default": {
          "url": "https://i.ytimg.com/vi/xEXNrjERBUM/default.jpg",
          "width": 120,
          "height": 90
        },
        "medium": {
          "url": "https://i.ytimg.com/vi/xEXNrjERBUM/mqdefault.jpg",
          "width": 320,
          "height": 180
        },
        "high": {
          "url": "https://i.ytimg.com/vi/xEXNrjERBUM/hqdefault.jpg",
          "width": 480,
          "height": 360
        },
        "standard": {
          "url": "https://i.ytimg.com/vi/xEXNrjERBUM/sddefault.jpg",
          "width": 640,
          "height": 480
        },
        "maxres": {
          "url": "https://i.ytimg.com/vi/xEXNrjERBUM/maxresdefault.jpg",
          "width": 1280,
          "height": 720
        }
      },
      "tags": [
        "source:영상",
        "type:방송",
        "genre:정치",
        "format:중계"
      ],
      "isShorts": true
    },
    {
      "id": "4Qb75OiQGxs",
      "channelId": "UChlgI3UHCOnwUGzWzbJ3H5w",
      "channelTitle": " YTN",
      "title": "정부, KT 영업정지·위약금 면제 등 검토 / YTN",
      "description": "정부가 무단 소액결제 피해가 일어난 KT 해킹 사태와 관련해 위약금 면제와 영업정지 등 제재 여부를 검토하겠다고 밝혔습니다.\n\n배경훈 과학기술정보통신부 장관은 국회 과학기술정보방송통신위원회 현안 질의에서 더불어민주당 황정아 의원이 KT에 대한 민관합동조사단의 결과가 발표되면 위약금 면제와 영업 정지 조치를 할 것인지 묻자 진행하겠다고 답했습니다.\n\n황 의원",
      "publishedAt": "2025-12-02T15:41:46Z",
      "duration": "PT39S",
      "durationSeconds": 39,
      "viewCount": 281,
      "likeCount": 3,
      "commentCount": 0,
      "thumbnails": {
        "default": {
          "url": "https://i.ytimg.com/vi/4Qb75OiQGxs/default.jpg",
          "width": 120,
          "height": 90
        },
        "medium": {
          "url": "https://i.ytimg.com/vi/4Qb75OiQGxs/mqdefault.jpg",
          "width": 320,
          "height": 180
        },
        "high": {
          "url": "https://i.ytimg.com/vi/4Qb75OiQGxs/hqdefault.jpg",
          "width": 480,
          "height": 360
        },
        "standard": {
          "url": "https://i.ytimg.com/vi/4Qb75OiQGxs/sddefault.jpg",
          "width": 640,
          "height": 480
        },
        "maxres": {
          "url": "https://i.ytimg.com/vi/4Qb75OiQGxs/maxresdefault.jpg",
          "width": 1280,
          "height": 720
        }
      },
      "tags": [
        "source:영상",
        "type:방송",
        "genre:경제",
        "format:단신",
        "person:박기완"
      ],
      "isShorts": true
    },
    {
      "id": "R5K5H1DS2UM",
      "channelId": "UChlgI3UHCOnwUGzWzbJ3H5w",
      "channelTitle": " YTN",
      "title": "[기업] '국내 최대 위성제조 허브' 한화 제주우주센터 준공 / YTN",
      "description": "한화시스템이 민간기업이 주도하는 국내 최대 규모 위성 생산기지인 제주우주센터 준공식을 열었습니다.\n\n제주 서귀포시 옛 탐라대 유휴부지에 자리 잡은 축구장 4개 크기의 한화 제주우주센터는 내년부터 연간 최대 100기의 위성을 생산하게 됩니다.\n\n최첨단 기술이 집약된 이곳 생산기지는 위성 개발·조립장과 성능 시험장, 우주센터 통제실 등을 갖추고 있으며 한화시스",
      "publishedAt": "2025-12-02T15:42:49Z",
      "duration": "PT20S",
      "durationSeconds": 20,
      "viewCount": 238,
      "likeCount": 1,
      "commentCount": 0,
      "thumbnails": {
        "default": {
          "url": "https://i.ytimg.com/vi/R5K5H1DS2UM/default.jpg",
          "width": 120,
          "height": 90
        },
        "medium": {
          "url": "https://i.ytimg.com/vi/R5K5H1DS2UM/mqdefault.jpg",
          "width": 320,
          "height": 180
        },
        "high": {
          "url": "https://i.ytimg.com/vi/R5K5H1DS2UM/hqdefault.jpg",
          "width": 480,
          "height": 360
        },
        "standard": {
          "url": "https://i.ytimg.com/vi/R5K5H1DS2UM/sddefault.jpg",
          "width": 640,
          "height": 480
        },
        "maxres": {
          "url": "https://i.ytimg.com/vi/R5K5H1DS2UM/maxresdefault.jpg",
          "width": 1280,
          "height": 720
        }
      },
      "tags": [
        "source:영상",
        "type:방송",
        "genre:경제",
        "format:단신",
        "person:이지은"
      ],
      "isShorts": true
    },
    {
      "id": "e9CMjNafgEs",
      "channelId": "UChlgI3UHCOnwUGzWzbJ3H5w",
      "channelTitle": " YTN",
      "title": "국민의힘 \"대장동 항소 포기 끝까지\"...국조요구서 제출 / YTN",
      "description": "국민의힘이 대장동 항소 포기 사태만큼은 지구 끝까지 쫓아가 파겠다며 국정조사 계획서를 국회에 제출했습니다.\n\n송언석 원내대표는 오늘(2일) 의원총회에서 항소 포기뿐 아니라 민주당 요구대로 조작 수사와 기소, 항명까지 모두 4건에 대해 국정조사를 하겠다고 했는데도 민주당은 얘기가 없다고 지적했습니다.\n\n이어 조작 기소니 항명이니 해도 검사와 법무부 장·차관,",
      "publishedAt": "2025-12-02T15:42:39Z",
      "duration": "PT38S",
      "durationSeconds": 38,
      "viewCount": 191,
      "likeCount": 1,
      "commentCount": 2,
      "thumbnails": {
        "default": {
          "url": "https://i.ytimg.com/vi/e9CMjNafgEs/default.jpg",
          "width": 120,
          "height": 90
        },
        "medium": {
          "url": "https://i.ytimg.com/vi/e9CMjNafgEs/mqdefault.jpg",
          "width": 320,
          "height": 180
        },
        "high": {
          "url": "https://i.ytimg.com/vi/e9CMjNafgEs/hqdefault.jpg",
          "width": 480,
          "height": 360
        },
        "standard": {
          "url": "https://i.ytimg.com/vi/e9CMjNafgEs/sddefault.jpg",
          "width": 640,
          "height": 480
        },
        "maxres": {
          "url": "https://i.ytimg.com/vi/e9CMjNafgEs/maxresdefault.jpg",
          "width": 1280,
          "height": 720
        }
      },
      "tags": [
        "source:영상",
        "type:방송",
        "genre:정치",
        "format:단신",
        "person:김다연"
      ],
      "isShorts": true
    },
    {
      "id": "7Ojmp9zor54",
      "channelId": "UChlgI3UHCOnwUGzWzbJ3H5w",
      "channelTitle": " YTN",
      "title": "여야, '개인정보 유출' 쿠팡 질타...\"민낯 드러나\"·\"괴도 루팡\" / YTN",
      "description": "여야는 쿠팡의 개인 정보 유출 사태에 대한 국회 과방위 긴급 현안질의에서 쿠팡의 부실 대응을 한목소리로 비판했습니다.\n\n더불어민주당은 한 해 매출액만 40조 원이 넘는 국내 전자상거래 1위 업체 쿠팡의 민낯이 드러난 한 해라며 개인 정보가 역대급으로 털렸는데도, 5개월 동안 인지하지 못했다고 질타했습니다.\n\n국민의힘도 이름·전화번호·주소까지 정보 '종합 세",
      "publishedAt": "2025-12-02T17:36:36Z",
      "duration": "PT36S",
      "durationSeconds": 36,
      "viewCount": 164,
      "likeCount": 4,
      "commentCount": 3,
      "thumbnails": {
        "default": {
          "url": "https://i.ytimg.com/vi/7Ojmp9zor54/default.jpg",
          "width": 120,
          "height": 90
        },
        "medium": {
          "url": "https://i.ytimg.com/vi/7Ojmp9zor54/mqdefault.jpg",
          "width": 320,
          "height": 180
        },
        "high": {
          "url": "https://i.ytimg.com/vi/7Ojmp9zor54/hqdefault.jpg",
          "width": 480,
          "height": 360
        },
        "standard": {
          "url": "https://i.ytimg.com/vi/7Ojmp9zor54/sddefault.jpg",
          "width": 640,
          "height": 480
        },
        "maxres": {
          "url": "https://i.ytimg.com/vi/7Ojmp9zor54/maxresdefault.jpg",
          "width": 1280,
          "height": 720
        }
      },
      "tags": [
        "source:영상",
        "type:방송",
        "genre:정치",
        "format:단신",
        "person:임성재"
      ],
      "isShorts": true
    },
    {
      "id": "IphmqJB70LE",
      "channelId": "UChlgI3UHCOnwUGzWzbJ3H5w",
      "channelTitle": " YTN",
      "title": "쿠팡 1조 원대 과징금 가능성...개보위 \"중점 검토\" / YTN",
      "description": "이정렬 개인정보보호위원회 부위원장은 쿠팡의 대규모 고객 개인정보 유출과 관련해 최대 1조 원대 과징금 부과 가능성에 대해 \"중점적으로 검토하고 있다\"고 밝혔습니다.\n\n이 부위원장은 국회 과학기술정보방송통신위원회 현안 질의에서 '결론적으로 1조 원 이상 과징금이 부과될 수 있는 것 아니냐'는 민주당 조인철 의원의 질의에 \"유출 등에 해당하기 때문에 과징금 부",
      "publishedAt": "2025-12-02T16:26:32Z",
      "duration": "PT44S",
      "durationSeconds": 44,
      "viewCount": 75,
      "likeCount": 0,
      "commentCount": 2,
      "thumbnails": {
        "default": {
          "url": "https://i.ytimg.com/vi/IphmqJB70LE/default.jpg",
          "width": 120,
          "height": 90
        },
        "medium": {
          "url": "https://i.ytimg.com/vi/IphmqJB70LE/mqdefault.jpg",
          "width": 320,
          "height": 180
        },
        "high": {
          "url": "https://i.ytimg.com/vi/IphmqJB70LE/hqdefault.jpg",
          "width": 480,
          "height": 360
        },
        "standard": {
          "url": "https://i.ytimg.com/vi/IphmqJB70LE/sddefault.jpg",
          "width": 640,
          "height": 480
        },
        "maxres": {
          "url": "https://i.ytimg.com/vi/IphmqJB70LE/maxresdefault.jpg",
          "width": 1280,
          "height": 720
        }
      },
      "tags": [
        "YTN실시간",
        "YTN"
      ],
      "isShorts": true
    },
    {
      "id": "WQfqqWQLntg",
      "channelId": "UChlgI3UHCOnwUGzWzbJ3H5w",
      "channelTitle": " YTN",
      "title": "배당소득 분리과세 개정안 국회 본회의 통과...\"50억 초과 시 세율 30%\" / YTN",
      "description": "배당소득 분리과세 50억 원 초과 구간을 신설하고 최고세율 30%를 적용하는 조세특례제한법 개정안이 국회 본회의를 통과했습니다.\n\n국회는 오늘(2일) 본회의에서 재석 243명 가운데 찬성 201명, 반대 18명, 기권 24명으로 법안을 가결했습니다.\n\n배당소득에 대해 구간별 분리과세를 도입한 것이 핵심으로, 2천만 원까지는 14%, 2천만 원 초과 3억 원",
      "publishedAt": "2025-12-02T18:06:37Z",
      "duration": "PT26S",
      "durationSeconds": 26,
      "viewCount": 32,
      "likeCount": 0,
      "commentCount": 0,
      "thumbnails": {
        "default": {
          "url": "https://i.ytimg.com/vi/WQfqqWQLntg/default.jpg",
          "width": 120,
          "height": 90
        },
        "medium": {
          "url": "https://i.ytimg.com/vi/WQfqqWQLntg/mqdefault.jpg",
          "width": 320,
          "height": 180
        },
        "high": {
          "url": "https://i.ytimg.com/vi/WQfqqWQLntg/hqdefault.jpg",
          "width": 480,
          "height": 360
        },
        "standard": {
          "url": "https://i.ytimg.com/vi/WQfqqWQLntg/sddefault.jpg",
          "width": 640,
          "height": 480
        },
        "maxres": {
          "url": "https://i.ytimg.com/vi/WQfqqWQLntg/maxresdefault.jpg",
          "width": 1280,
          "height": 720
        }
      },
      "tags": [
        "source:영상",
        "type:방송",
        "genre:정치",
        "format:단신",
        "person:박광렬"
      ],
      "isShorts": true
    },
    {
      "id": "EPOt04B3Cvg",
      "channelId": "UChlgI3UHCOnwUGzWzbJ3H5w",
      "channelTitle": " YTN",
      "title": "'대북전단 살포 규제' 항공안전법, 여권 주도 본회의 통과 / YTN",
      "description": "비행금지구역에서 대북전단 살포용 풍선을 비롯한 무인자유기구 비행을 금지하는 법안이 범여권 주도로 국회 본회의를 통과했습니다.\n\n국회는 오늘(2일) 본회의에서 이 같은 내용의 항공안전법 개정안을 재석 234인 가운데 찬성 156표, 반대 77표, 기권 1표로 가결했습니다.\n\n표결 전 토론에서 국민의힘 이종욱 의원은 위헌 결정이 내려진 '대북전단 금지법'을 부",
      "publishedAt": "2025-12-02T18:07:35Z",
      "duration": "PT38S",
      "durationSeconds": 38,
      "viewCount": 30,
      "likeCount": 1,
      "commentCount": 1,
      "thumbnails": {
        "default": {
          "url": "https://i.ytimg.com/vi/EPOt04B3Cvg/default.jpg",
          "width": 120,
          "height": 90
        },
        "medium": {
          "url": "https://i.ytimg.com/vi/EPOt04B3Cvg/mqdefault.jpg",
          "width": 320,
          "height": 180
        },
        "high": {
          "url": "https://i.ytimg.com/vi/EPOt04B3Cvg/hqdefault.jpg",
          "width": 480,
          "height": 360
        },
        "standard": {
          "url": "https://i.ytimg.com/vi/EPOt04B3Cvg/sddefault.jpg",
          "width": 640,
          "height": 480
        },
        "maxres": {
          "url": "https://i.ytimg.com/vi/EPOt04B3Cvg/maxresdefault.jpg",
          "width": 1280,
          "height": 720
        }
      },
      "tags": [
        "source:영상",
        "type:방송",
        "genre:정치",
        "format:단신",
        "person:박희재"
      ],
      "isShorts": true
    }
  ]
}