{
  "lastUpdated": "2026-05-25T19:15:28.064Z",
  "totalChannelsAnalyzed": 43,
  "totalVideos": 30,
  "totalShorts": 10,
  "totalRegularVideos": 20,
  "totalViewCount": 1733060,
  "totalLikeCount": 48225,
  "averageViewsPerShort": 108928,
  "topChannelsByShorts": [
    {
      "title": "엠키타카 MKTK",
      "shortsCount": 10,
      "subscriberCount": 1070000
    }
  ],
  "topShortsByViews": [
    {
      "title": "\"반성할 줄 알아야 해!!\"",
      "channelTitle": "엠키타카 MKTK",
      "viewCount": 448597,
      "publishedAt": "2026-05-24T01:30:23Z"
    },
    {
      "title": "\"여기 변해야 돼요!!\"",
      "channelTitle": "엠키타카 MKTK",
      "viewCount": 161121,
      "publishedAt": "2026-05-24T00:00:30Z"
    },
    {
      "title": "국힘 못 뽑겠는(?) 이유",
      "channelTitle": "엠키타카 MKTK",
      "viewCount": 156714,
      "publishedAt": "2026-05-24T03:00:01Z"
    },
    {
      "title": "제정신?",
      "channelTitle": "엠키타카 MKTK",
      "viewCount": 109811,
      "publishedAt": "2026-05-23T03:00:07Z"
    },
    {
      "title": "식겁한 경호원",
      "channelTitle": "엠키타카 MKTK",
      "viewCount": 87903,
      "publishedAt": "2026-05-23T23:13:40Z"
    },
    {
      "title": "\"민주당 별로 안 좋아하는데..\"",
      "channelTitle": "엠키타카 MKTK",
      "viewCount": 38568,
      "publishedAt": "2026-05-25T04:00:01Z"
    },
    {
      "title": "\"하동은 다 죽었어요..\"",
      "channelTitle": "엠키타카 MKTK",
      "viewCount": 33996,
      "publishedAt": "2026-05-25T03:00:36Z"
    },
    {
      "title": "스벅 본사도 사과했는데..",
      "channelTitle": "엠키타카 MKTK",
      "viewCount": 31523,
      "publishedAt": "2026-05-23T00:00:07Z"
    },
    {
      "title": "이 공연 의도가 뭐예요;;",
      "channelTitle": "엠키타카 MKTK",
      "viewCount": 11911,
      "publishedAt": "2026-05-22T12:00:17Z"
    },
    {
      "title": "8년만에 재매치..!",
      "channelTitle": "엠키타카 MKTK",
      "viewCount": 9135,
      "publishedAt": "2026-05-22T10:00:33Z"
    }
  ]
}