{
  "lastUpdated": "2026-01-16T18:20:54.886Z",
  "totalChannelsAnalyzed": 82,
  "totalVideos": 30,
  "totalShorts": 29,
  "totalRegularVideos": 1,
  "totalViewCount": 15338946,
  "totalLikeCount": 377652,
  "averageViewsPerShort": 524767,
  "topChannelsByShorts": [
    {
      "title": "이마까TV",
      "shortsCount": 29,
      "subscriberCount": 337000
    }
  ],
  "topShortsByViews": [
    {
      "title": "민주당의 통일교 특검 수용, 국힘당 반응",
      "channelTitle": "이마까TV",
      "viewCount": 1907206,
      "publishedAt": "2025-12-22T04:06:43Z"
    },
    {
      "title": "계엄 당일, 경찰 녹취 \"국회의장도 통제하라\"",
      "channelTitle": "이마까TV",
      "viewCount": 1620027,
      "publishedAt": "2026-01-08T11:06:21Z"
    },
    {
      "title": "윤석열 구형을 본 대만방송 솔직반응",
      "channelTitle": "이마까TV",
      "viewCount": 1019346,
      "publishedAt": "2026-01-15T15:49:24Z"
    },
    {
      "title": "국힘당 베네수엘라 타령 팩트로 입틀막",
      "channelTitle": "이마까TV",
      "viewCount": 1015342,
      "publishedAt": "2026-01-05T21:35:45Z"
    },
    {
      "title": "오세훈 쉴드치다 질문 한방에 어버버",
      "channelTitle": "이마까TV",
      "viewCount": 968588,
      "publishedAt": "2026-01-02T08:01:07Z"
    },
    {
      "title": "국힘당 탈출은 지능순이라는 민주패널",
      "channelTitle": "이마까TV",
      "viewCount": 922080,
      "publishedAt": "2025-12-31T03:22:24Z"
    },
    {
      "title": "행정의 대가 이재명, 부산 해수부 개청식",
      "channelTitle": "이마까TV",
      "viewCount": 819715,
      "publishedAt": "2025-12-24T03:17:30Z"
    },
    {
      "title": "이혜훈 찬반을 떠나 보수분열 효과는 확실",
      "channelTitle": "이마까TV",
      "viewCount": 782170,
      "publishedAt": "2025-12-29T09:02:01Z"
    },
    {
      "title": "잘 돌아가는 윤석열 내란재판",
      "channelTitle": "이마까TV",
      "viewCount": 732647,
      "publishedAt": "2025-12-24T13:01:00Z"
    },
    {
      "title": "국힘당 심리상태? 허탈 좌절 무기력?",
      "channelTitle": "이마까TV",
      "viewCount": 717065,
      "publishedAt": "2026-01-04T10:18:52Z"
    }
  ]
}