{
  "lastUpdated": "2025-10-03T12:22:45.870Z",
  "totalChannelsAnalyzed": 85,
  "totalVideos": 780,
  "totalShorts": 552,
  "totalRegularVideos": 228,
  "totalViewCount": 184229333,
  "totalLikeCount": 6354844,
  "averageViewsPerShort": 290172,
  "topChannelsByShorts": [
    {
      "title": "미디어쇼츠 ",
      "shortsCount": 30,
      "subscriberCount": 292000
    },
    {
      "title": "나의조국",
      "shortsCount": 30,
      "subscriberCount": 280000
    },
    {
      "title": "이잼TV",
      "shortsCount": 30,
      "subscriberCount": 195000
    },
    {
      "title": "궁금증해결",
      "shortsCount": 30,
      "subscriberCount": 109000
    },
    {
      "title": "이슈이슈특공대",
      "shortsCount": 30,
      "subscriberCount": 45600
    },
    {
      "title": "세상만사",
      "shortsCount": 29,
      "subscriberCount": 612000
    },
    {
      "title": "한국의목소리",
      "shortsCount": 29,
      "subscriberCount": 465000
    },
    {
      "title": "옳소TV",
      "shortsCount": 29,
      "subscriberCount": 407000
    },
    {
      "title": "정치일주",
      "shortsCount": 29,
      "subscriberCount": 250000
    },
    {
      "title": "지구뉴스(Jigu News)",
      "shortsCount": 29,
      "subscriberCount": 114000
    }
  ],
  "topShortsByViews": [
    {
      "title": "\"무식한 윤석열 변호사\"를 \"논리로 때려잡는 특검검사\"",
      "channelTitle": "정치일주",
      "viewCount": 4985119,
      "publishedAt": "2025-09-26T23:58:00Z"
    },
    {
      "title": "고인이 된 전유성 KBS 노제 위해 모인 개그맨 후배들 #shorts #최양락 #남희석 #김수용 #조세호",
      "channelTitle": "미디어쇼츠 ",
      "viewCount": 4093294,
      "publishedAt": "2025-09-28T05:31:31Z"
    },
    {
      "title": "\"김광민 변호사\" 협박한 \"검사 박상용\"",
      "channelTitle": "정치일주",
      "viewCount": 3579156,
      "publishedAt": "2025-09-25T22:12:00Z"
    },
    {
      "title": "전유성 선배 kbs 노제 함께하는 조정현 엄영수 이영자 #shorts #이영자 #전유성 #개그콘서트 #노제",
      "channelTitle": "미디어쇼츠 ",
      "viewCount": 3475754,
      "publishedAt": "2025-09-28T14:20:37Z"
    },
    {
      "title": "\"바보 선언 동영상\" 말하는 대로 이뤄진다",
      "channelTitle": "정치일주",
      "viewCount": 3180343,
      "publishedAt": "2025-09-27T22:07:00Z"
    },
    {
      "title": "맞먹으려드는 '부하출신' 국힘 의원들 옛날 생각나게 해주는 4성 장군 출신 김병주",
      "channelTitle": "더민숏전시관",
      "viewCount": 3115583,
      "publishedAt": "2025-09-21T02:48:51Z"
    },
    {
      "title": "당신들이 법사위원 '자격'이 있냐며 시비터는 신동욱 아작내버리는 박은정",
      "channelTitle": "더민숏전시관",
      "viewCount": 2997068,
      "publishedAt": "2025-09-26T02:31:49Z"
    },
    {
      "title": "재판일정 갖다가 시비터는 윤석열 변호인 참교육 해버리는 백대현 부장판사",
      "channelTitle": "더민숏전시관",
      "viewCount": 2820926,
      "publishedAt": "2025-09-28T08:23:04Z"
    },
    {
      "title": "일본이 5500억 달러 주면 미국은 어떻게 쓸까",
      "channelTitle": "지구뉴스(Jigu News)",
      "viewCount": 2653095,
      "publishedAt": "2025-09-29T15:06:06Z"
    },
    {
      "title": "귀를 의심케 하는 계몽녀의 뻘소리",
      "channelTitle": "민주픽",
      "viewCount": 2515511,
      "publishedAt": "2025-09-30T13:00:03Z"
    }
  ]
}